{
    "misc": {
        "step_x": "گام [number]",
        "step_x_description": "گام [number]: [description]",
        "overview": {
            "tutorial_x_title": "آموزش [number]: [title]",
            "summary": "اف‌دروید فروشگاه کاره‌ای مستقل و مبتنی بر جامعه برای اندروید بوده که کاملاً نرم‌افزار آزاد است. با اف‌دروید می‌توانید بیش از ۱٫۲۰۰ کارهٔ آزاد را از میان مخازن موجود مرور، جست‌وجو و نصب کرده، یا مخازن خودتان را بسازید. برای بارگیری کاره و شروع به کار f-droid.org را روی تلفن اندرودیتان  بگشایید!",
            "title": "با اف‌دروید می‌شود چه‌کار کرد"
        },
        "option_x_description": "گزینهٔ [number]: [description]"
    },
    "add_repo": {
        "overview": {
            "title": "گرفتن محتوای بیش‌تر."
        }
    }
}
